<?xml version="1.0" encoding="utf-8" ?>
<dwsync>
<file name="array_helper.php" server="74.52.31.66/public_html/" local="130679953925617215" remote="130750027800000000" Dst="2" />
<file name="captcha_helper.php" server="74.52.31.66/public_html/" local="130679953925617215" remote="130750027800000000" Dst="2" />
<file name="cookie_helper.php" server="74.52.31.66/public_html/" local="130679953925773477" remote="130750027800000000" Dst="2" />
<file name="date_helper.php" server="74.52.31.66/public_html/" local="130679953926085992" remote="130750027800000000" Dst="2" />
<file name="directory_helper.php" server="74.52.31.66/public_html/" local="130679953926085992" remote="130750027800000000" Dst="2" />
<file name="download_helper.php" server="74.52.31.66/public_html/" local="130679953926242245" remote="130750027800000000" Dst="2" />
<file name="email_helper.php" server="74.52.31.66/public_html/" local="130679953926398507" remote="130750027800000000" Dst="2" />
<file name="file_helper.php" server="74.52.31.66/public_html/" local="130679953926554768" remote="130750027800000000" Dst="2" />
<file name="form_helper.php" server="74.52.31.66/public_html/" local="130679953926711018" remote="130750027800000000" Dst="2" />
<file name="html_helper.php" server="74.52.31.66/public_html/" local="130679953926867280" remote="130750027800000000" Dst="2" />
<file name="index.html" server="74.52.31.66/public_html/" local="130679953927023537" remote="130750027800000000" Dst="2" />
<file name="inflector_helper.php" server="74.52.31.66/public_html/" local="130679953927023537" remote="130750027800000000" Dst="2" />
<file name="language_helper.php" server="74.52.31.66/public_html/" local="130679953927179799" remote="130750027800000000" Dst="2" />
<file name="number_helper.php" server="74.52.31.66/public_html/" local="130679953927336060" remote="130750027800000000" Dst="2" />
<file name="path_helper.php" server="74.52.31.66/public_html/" local="130679953927492326" remote="130750027800000000" Dst="2" />
<file name="security_helper.php" server="74.52.31.66/public_html/" local="130679953927648591" remote="130750027800000000" Dst="2" />
<file name="smiley_helper.php" server="74.52.31.66/public_html/" local="130679953927648591" remote="130750027800000000" Dst="2" />
<file name="string_helper.php" server="74.52.31.66/public_html/" local="130679953927804849" remote="130750027800000000" Dst="2" />
<file name="text_helper.php" server="74.52.31.66/public_html/" local="130679953927961079" remote="130750027800000000" Dst="2" />
<file name="typography_helper.php" server="74.52.31.66/public_html/" local="130679953928117340" remote="130750027800000000" Dst="2" />
<file name="url_helper.php" server="74.52.31.66/public_html/" local="130679953928273610" remote="130750027800000000" Dst="2" />
<file name="xml_helper.php" server="74.52.31.66/public_html/" local="130679953928429875" remote="130750027800000000" Dst="2" />
</dwsync>