<?xml version="1.0" encoding="utf-8" ?>
<dwsync>
<file name="downloads.html" server="74.52.31.66/public_html/" local="130679953946088996" remote="130750028400000000" Dst="2" />
<file name="index.html" server="74.52.31.66/public_html/" local="130679953946245253" remote="130750028400000000" Dst="2" />
<file name="troubleshooting.html" server="74.52.31.66/public_html/" local="130679953946401542" remote="130750028400000000" Dst="2" />
<file name="upgrade_120.html" server="74.52.31.66/public_html/" local="130679953946401542" remote="130750028400000000" Dst="2" />
<file name="upgrade_130.html" server="74.52.31.66/public_html/" local="130679953946557788" remote="130750028400000000" Dst="2" />
<file name="upgrade_131.html" server="74.52.31.66/public_html/" local="130679953946714054" remote="130750028400000000" Dst="2" />
<file name="upgrade_132.html" server="74.52.31.66/public_html/" local="130679953946714054" remote="130750028400000000" Dst="2" />
<file name="upgrade_133.html" server="74.52.31.66/public_html/" local="130679953946870307" remote="130750028400000000" Dst="2" />
<file name="upgrade_140.html" server="74.52.31.66/public_html/" local="130679953947026545" remote="130750028400000000" Dst="2" />
<file name="upgrade_141.html" server="74.52.31.66/public_html/" local="130679953947182811" remote="130750028400000000" Dst="2" />
<file name="upgrade_150.html" server="74.52.31.66/public_html/" local="130679953947339092" remote="130750028400000000" Dst="2" />
<file name="upgrade_152.html" server="74.52.31.66/public_html/" local="130679953947339092" remote="130750028400000000" Dst="2" />
<file name="upgrade_153.html" server="74.52.31.66/public_html/" local="130679953947495318" remote="130750028400000000" Dst="2" />
<file name="upgrade_154.html" server="74.52.31.66/public_html/" local="130679953947651611" remote="130750028400000000" Dst="2" />
<file name="upgrade_160.html" server="74.52.31.66/public_html/" local="130679953947651611" remote="130750028400000000" Dst="2" />
<file name="upgrade_161.html" server="74.52.31.66/public_html/" local="130679953947807829" remote="130750028400000000" Dst="2" />
<file name="upgrade_162.html" server="74.52.31.66/public_html/" local="130679953947964107" remote="130750028400000000" Dst="2" />
<file name="upgrade_163.html" server="74.52.31.66/public_html/" local="130679953948120372" remote="130750028400000000" Dst="2" />
<file name="upgrade_170.html" server="74.52.31.66/public_html/" local="130679953948120372" remote="130750028400000000" Dst="2" />
<file name="upgrade_171.html" server="74.52.31.66/public_html/" local="130679953948276606" remote="130750028400000000" Dst="2" />
<file name="upgrade_172.html" server="74.52.31.66/public_html/" local="130679953948432867" remote="130750028400000000" Dst="2" />
<file name="upgrade_200.html" server="74.52.31.66/public_html/" local="130679953948589125" remote="130750028400000000" Dst="2" />
<file name="upgrade_201.html" server="74.52.31.66/public_html/" local="130679953948589125" remote="130750028400000000" Dst="2" />
<file name="upgrade_202.html" server="74.52.31.66/public_html/" local="130679953948745379" remote="130750028400000000" Dst="2" />
<file name="upgrade_203.html" server="74.52.31.66/public_html/" local="130679953948901656" remote="130750028400000000" Dst="2" />
<file name="upgrade_210.html" server="74.52.31.66/public_html/" local="130679953948901656" remote="130750028400000000" Dst="2" />
<file name="upgrade_211.html" server="74.52.31.66/public_html/" local="130679953949057918" remote="130750028400000000" Dst="2" />
<file name="upgrade_212.html" server="74.52.31.66/public_html/" local="130679953949214147" remote="130750028400000000" Dst="2" />
<file name="upgrade_213.html" server="74.52.31.66/public_html/" local="130679953949370421" remote="130750028400000000" Dst="2" />
<file name="upgrade_214.html" server="74.52.31.66/public_html/" local="130679953949526671" remote="130750028400000000" Dst="2" />
<file name="upgrade_220.html" server="74.52.31.66/public_html/" local="130679953949526671" remote="130750028400000000" Dst="2" />
<file name="upgrade_221.html" server="74.52.31.66/public_html/" local="130679953949682924" remote="130750028400000000" Dst="2" />
<file name="upgrade_b11.html" server="74.52.31.66/public_html/" local="130679953949839198" remote="130750028400000000" Dst="2" />
<file name="upgrading.html" server="74.52.31.66/public_html/" local="130679953949839198" remote="130750028400000000" Dst="2" />
</dwsync>